odoo/addons/mail_activity_board/README.rst
odoo/addons/mail_activity_board/__init__.py
odoo/addons/mail_activity_board/__manifest__.py
odoo/addons/mail_activity_board/i18n/ca.po
odoo/addons/mail_activity_board/i18n/es.po
odoo/addons/mail_activity_board/i18n/fr.po
odoo/addons/mail_activity_board/i18n/fr_BE.po
odoo/addons/mail_activity_board/i18n/it.po
odoo/addons/mail_activity_board/i18n/mail_activity_board.pot
odoo/addons/mail_activity_board/i18n/pt.po
odoo/addons/mail_activity_board/migrations/18.0.1.1.0/pre-migration.py
odoo/addons/mail_activity_board/models/__init__.py
odoo/addons/mail_activity_board/models/mail_activity.py
odoo/addons/mail_activity_board/models/mail_activity_mixin.py
odoo/addons/mail_activity_board/readme/CONTRIBUTORS.md
odoo/addons/mail_activity_board/readme/DESCRIPTION.md
odoo/addons/mail_activity_board/readme/USAGE.md
odoo/addons/mail_activity_board/static/description/icon.png
odoo/addons/mail_activity_board/static/description/index.html
odoo/addons/mail_activity_board/static/src/components/chatter/chatter.esm.js
odoo/addons/mail_activity_board/static/src/components/chatter/chatter.xml
odoo/addons/mail_activity_board/tests/__init__.py
odoo/addons/mail_activity_board/tests/test_mail_activity_board.py
odoo/addons/mail_activity_board/views/mail_activity_view.xml
odoo_addon_mail_activity_board-18.0.1.1.1.dist-info/METADATA
odoo_addon_mail_activity_board-18.0.1.1.1.dist-info/WHEEL
odoo_addon_mail_activity_board-18.0.1.1.1.dist-info/top_level.txt
odoo_addon_mail_activity_board-18.0.1.1.1.dist-info/RECORD
